mirofile/__init__.py
mirofile/mirofile.py
mirofile-0.1.dist-info/METADATA
mirofile-0.1.dist-info/WHEEL
mirofile-0.1.dist-info/licenses/LICENSE
mirofile-0.1.dist-info/RECORD
