Metadata-Version: 2.3
Name: mirofile
Version: 0.1
Summary: Python module for using MIROSLAV files as file-like objects with seamless preprocessing. MIROSLAV is a FOSS tool for monitoring activity of laboratory rodents.
Project-URL: Homepage, https://github.com/davorvr/mirofile
Project-URL: Bug Tracker, https://github.com/davorvr/mirofile/issues
Author-email: Davor Virag <davor.virag@gmail.com>
License-File: LICENSE
Classifier: Intended Audience :: Science/Research
Classifier: License :: OSI Approved :: GNU General Public License v3 (GPLv3)
Classifier: Operating System :: OS Independent
Classifier: Programming Language :: Python :: 3
Classifier: Topic :: Scientific/Engineering
Requires-Python: >=3.12
Requires-Dist: tqdm>=4.66.2
